utils/PRUEBAS.py
utils/__init__.py
utils/dicts.py
utils/lists.py
utils/strings.py
utils/query_builder/__init__.py
utils/query_builder/mysql.py
estratega_utils-2.0.dist-info/METADATA
estratega_utils-2.0.dist-info/WHEEL
estratega_utils-2.0.dist-info/top_level.txt
estratega_utils-2.0.dist-info/RECORD
