Metadata-Version: 2.1
Name: estratega-utils
Version: 2.0
Summary: Utilidades varias
Author: Ivan Sayavedra
Author-email: <isayavedra@estrategasoftware.com.ar>
Keywords: python,estratega utils
Classifier: Development Status :: 3 - Alpha
Classifier: Intended Audience :: Education
Classifier: Programming Language :: Python :: 3
Classifier: Operating System :: Microsoft :: Windows
Requires-Dist: pydantic
Requires-Dist: pymysql
